layint_runtime_api/__init__.py
layint_runtime_api/api_client.py
layint_runtime_api/configuration.py
layint_runtime_api/rest.py
layint_runtime_api/apis/__init__.py
layint_runtime_api/apis/configuration_api.py
layint_runtime_api/apis/container_api.py
layint_runtime_api/apis/event_api.py
layint_runtime_api/apis/image_api.py
layint_runtime_api/apis/policy_api.py
layint_runtime_api/apis/registry_api.py
layint_runtime_api/models/__init__.py
layint_runtime_api/models/alert_events.py
layint_runtime_api/models/config.py
layint_runtime_api/models/configs.py
layint_runtime_api/models/container.py
layint_runtime_api/models/container_log.py
layint_runtime_api/models/container_logs.py
layint_runtime_api/models/containers.py
layint_runtime_api/models/dossier.py
layint_runtime_api/models/dossier_template_response.py
layint_runtime_api/models/image.py
layint_runtime_api/models/images.py
layint_runtime_api/models/inline_response_200.py
layint_runtime_api/models/limit.py
layint_runtime_api/models/policies.py
layint_runtime_api/models/policy.py
layint_runtime_api/models/policy_rule.py
layint_runtime_api/models/process_limit.py
layint_runtime_api/models/registries.py
layint_runtime_api/models/registry.py
layint_runtime_api/models/resource_not_found_error.py
layint_runtime_api/models/syscall_limit.py
layint_runtime_api/models/unauthorized_error.py
layint_runtime_api/models/update_config.py
layint_runtime_api-0.9.6.dist-info/DESCRIPTION.rst
layint_runtime_api-0.9.6.dist-info/METADATA
layint_runtime_api-0.9.6.dist-info/RECORD
layint_runtime_api-0.9.6.dist-info/WHEEL
layint_runtime_api-0.9.6.dist-info/metadata.json
layint_runtime_api-0.9.6.dist-info/top_level.txt
test/__init__.py
test/test_alert_events.py
test/test_config.py
test/test_configs.py
test/test_configuration_api.py
test/test_container.py
test/test_container_api.py
test/test_container_log.py
test/test_container_logs.py
test/test_containers.py
test/test_dossier.py
test/test_dossier_template_response.py
test/test_event_api.py
test/test_image.py
test/test_image_api.py
test/test_images.py
test/test_inline_response_200.py
test/test_limit.py
test/test_policies.py
test/test_policy.py
test/test_policy_api.py
test/test_policy_rule.py
