Metadata-Version: 2.0
Name: layint-runtime-api
Version: 0.9.6
Summary: Layered Witness &amp; Control
Home-page: UNKNOWN
Author: UNKNOWN
Author-email: help@layeredinsight.com
License: UNKNOWN
Keywords: Swagger,Layered Witness &amp; Control
Platform: UNKNOWN
Requires-Dist: urllib3 (>=1.15)
Requires-Dist: six (>=1.10)
Requires-Dist: certifi
Requires-Dist: python-dateutil
